scm_python_ms/lib/ssz_micro_service.py
scm_python_ms/tapps/ssz_micro_service/__init__.py
scm_python_ms/tapps/ssz_micro_service/context_processor.py
scm_python_ms/tapps/ssz_micro_service/etc_processor.py
scm_python_ms/tapps/ssz_micro_service/jar_processor.py
scm_python_ms/tapps/ssz_micro_service/ssh_processor.py
scm_python_ms/tapps/ssz_micro_service/printer/__init__.py
scm_python_ms/tapps/ssz_micro_service/printer/simple_printer.py
scm_python_ms-0.1.0.dist-info/METADATA
scm_python_ms-0.1.0.dist-info/WHEEL
scm_python_ms-0.1.0.dist-info/top_level.txt
scm_python_ms-0.1.0.dist-info/RECORD
